formchen/README.md
formchen/__init__.py
formchen/formchen-internal.d.ts
formchen/formchen.d.ts
formchen/index.js
formchen/package.json
formchen/webcomponent.js
formchen/tests/test_Formchen.js
formchen/tests/test_empty_object.js
formchen/tests/test_master_detail.js
formchen/tests/test_proxynode.js
formchen-0.1.6.dist-info/LICENSE
formchen-0.1.6.dist-info/METADATA
formchen-0.1.6.dist-info/WHEEL
formchen-0.1.6.dist-info/top_level.txt
formchen-0.1.6.dist-info/RECORD
