Metadata-Version: 2.1
Name: formchen
Version: 0.1.6
Summary: Generate HTML forms and bind hierarchical and tabular data.
Home-page: https://github.com/decatur/formchen
Author: Wolfgang Kühn
License: UNKNOWN
Platform: UNKNOWN
Requires-Python: >=3.6,<4.0
Requires-Dist: gridchen (<0.2.0,>=0.1.3)
